voronoi_scatter.py
voronoi_scatter-1.0.dist-info/LICENSE
voronoi_scatter-1.0.dist-info/METADATA
voronoi_scatter-1.0.dist-info/WHEEL
voronoi_scatter-1.0.dist-info/top_level.txt
voronoi_scatter-1.0.dist-info/RECORD
